odoo/addons/purchase_mass_mail/README.rst
odoo/addons/purchase_mass_mail/__init__.py
odoo/addons/purchase_mass_mail/__manifest__.py
odoo/addons/purchase_mass_mail/i18n/es.po
odoo/addons/purchase_mass_mail/i18n/it.po
odoo/addons/purchase_mass_mail/i18n/purchase_mass_mail.pot
odoo/addons/purchase_mass_mail/models/__init__.py
odoo/addons/purchase_mass_mail/models/purchase_order.py
odoo/addons/purchase_mass_mail/readme/CONTRIBUTORS.md
odoo/addons/purchase_mass_mail/readme/DESCRIPTION.md
odoo/addons/purchase_mass_mail/readme/USAGE.md
odoo/addons/purchase_mass_mail/static/description/icon.png
odoo/addons/purchase_mass_mail/static/description/index.html
odoo/addons/purchase_mass_mail/tests/__init__.py
odoo/addons/purchase_mass_mail/tests/test_send_mass_mail.py
odoo/addons/purchase_mass_mail/view/purchase_order.xml
odoo/addons/purchase_mass_mail/wizards/__init__.py
odoo/addons/purchase_mass_mail/wizards/mail_compose_message.py
odoo_addon_purchase_mass_mail-17.0.1.0.0.4.dist-info/METADATA
odoo_addon_purchase_mass_mail-17.0.1.0.0.4.dist-info/WHEEL
odoo_addon_purchase_mass_mail-17.0.1.0.0.4.dist-info/top_level.txt
odoo_addon_purchase_mass_mail-17.0.1.0.0.4.dist-info/RECORD
